[
  {
    "ContainingType": "FeedbackController",
    "Method": "GetAllFeedbacks",
    "RelativePath": "api/Feedback/all-feedbacks",
    "HttpMethod": "GET",
    "IsController": true,
    "Order": 0,
    "Parameters": [],
    "ReturnTypes": []
  },
  {
    "ContainingType": "FeedbackController",
    "Method": "ApproveAllPending",
    "RelativePath": "api/Feedback/approve-all",
    "HttpMethod": "PATCH",
    "IsController": true,
    "Order": 0,
    "Parameters": [],
    "ReturnTypes": []
  },
  {
    "ContainingType": "FeedbackController",
    "Method": "ApproveFeedback",
    "RelativePath": "api/Feedback/approve/{id}",
    "HttpMethod": "PATCH",
    "IsController": true,
    "Order": 0,
    "Parameters": [
      {
        "Name": "id",
        "Type": "System.Int32",
        "IsRequired": true
      }
    ],
    "ReturnTypes": []
  },
  {
    "ContainingType": "FeedbackController",
    "Method": "GetApprovedFeedbacks",
    "RelativePath": "api/Feedback/approved-feedbacks",
    "HttpMethod": "GET",
    "IsController": true,
    "Order": 0,
    "Parameters": [],
    "ReturnTypes": []
  },
  {
    "ContainingType": "FeedbackController",
    "Method": "GetAllUsers",
    "RelativePath": "api/Feedback/GetAllUsers",
    "HttpMethod": "GET",
    "IsController": true,
    "Order": 0,
    "Parameters": [],
    "ReturnTypes": []
  },
  {
    "ContainingType": "FeedbackController",
    "Method": "GetMyFeedbacks",
    "RelativePath": "api/Feedback/my-feedbacks",
    "HttpMethod": "GET",
    "IsController": true,
    "Order": 0,
    "Parameters": [],
    "ReturnTypes": []
  },
  {
    "ContainingType": "FeedbackController",
    "Method": "SubmitFeedback",
    "RelativePath": "api/Feedback/submit-feedback",
    "HttpMethod": "POST",
    "IsController": true,
    "Order": 0,
    "Parameters": [
      {
        "Name": "dto",
        "Type": "UseCase.Models.DTOS.FeedbackDTO",
        "IsRequired": true
      }
    ],
    "ReturnTypes": []
  },
  {
    "ContainingType": "UseCase.Controllers.UserLoginController",
    "Method": "Login",
    "RelativePath": "api/UserLogin/login",
    "HttpMethod": "POST",
    "IsController": true,
    "Order": 0,
    "Parameters": [
      {
        "Name": "dto",
        "Type": "UseCase.Models.DTOS.UserDTO",
        "IsRequired": true
      }
    ],
    "ReturnTypes": []
  },
  {
    "ContainingType": "UseCase.Controllers.UserLoginController",
    "Method": "Register",
    "RelativePath": "api/UserLogin/register",
    "HttpMethod": "POST",
    "IsController": true,
    "Order": 0,
    "Parameters": [
      {
        "Name": "dto",
        "Type": "UseCase.Models.DTOS.UserDTO",
        "IsRequired": true
      }
    ],
    "ReturnTypes": []
  }
]